diffmind/__init__.py
diffmind/cli.py
diffmind/config.py
diffmind/emoji.py
diffmind/generator.py
diffmind/hooks.py
diffmind/providers/base.py
diffmind/providers/openai_provider.py
diffmind/providers/simple.py
diffmind/refiner.py
diffmind/ui.py
diffmind/utils/git.py
diffmind-0.1.0.dist-info/METADATA
diffmind-0.1.0.dist-info/WHEEL
diffmind-0.1.0.dist-info/entry_points.txt
diffmind-0.1.0.dist-info/RECORD
