Metadata-Version: 2.3
Name: diffmind
Version: 0.1.0
Summary: AI-powered commit message generator (CLI + git hook) with delightful terminal UX
License: MIT
Keywords: git,commit,cli,hook,openai,ai,productivity
Author: DiffMind Contributors
Author-email: random1k11@gmail.com
Requires-Python: >=3.8,<4.0
Classifier: Development Status :: 3 - Alpha
Classifier: Environment :: Console
Classifier: Intended Audience :: Developers
Classifier: License :: OSI Approved :: MIT License
Classifier: Programming Language :: Python :: 3
Classifier: Programming Language :: Python :: 3.8
Classifier: Programming Language :: Python :: 3.9
Classifier: Programming Language :: Python :: 3.10
Classifier: Programming Language :: Python :: 3.11
Classifier: Programming Language :: Python :: 3.12
Classifier: Programming Language :: Python :: 3.13
Classifier: Programming Language :: Python :: 3 :: Only
Classifier: Topic :: Software Development :: Version Control :: Git
Provides-Extra: ai
Requires-Dist: InquirerPy (>=0.3.4,<0.4.0)
Requires-Dist: gitpython (>=3.1.43,<4.0.0)
Requires-Dist: openai (>=1.0.0) ; extra == "ai"
Requires-Dist: pydantic (>=2.8.2,<3.0.0)
Requires-Dist: rich (>=13.7.1,<14.0.0)
Requires-Dist: tomli (>=2.0.1,<3.0.0) ; python_version < "3.11"
Requires-Dist: typer[all] (>=0.12.3,<0.13.0)
Requires-Dist: typing-extensions (>=4.12.2,<5.0.0)
